GUI/__init__.py
GUI/bleachwindow_gui.py
GUI/convert_ui_files.py
GUI/correctionwindow_gui.py
GUI/cropwindow_gui.py
GUI/detectwindow_gui.py
GUI/exportsettings_gui.py
GUI/exportwindow_gui.py
GUI/filterwindow_gui.py
GUI/fittingwindow_gui.py
GUI/groupwindow_gui.py
GUI/importwindow_gui.py
GUI/mainwindow_gui.py
GUI/managewindow_gui.py
GUI/plotsettings_gui.py
GUI/simulatorwindow_gui.py
GUI/smoothingwindow_gui.py
TraceAnalyser/__init__.py
TraceAnalyser/main_window.py
TraceAnalyser/DeepFretSimulate/__init__.py
TraceAnalyser/DeepFretSimulate/math.py
TraceAnalyser/DeepFretSimulate/simulate.py
TraceAnalyser/DeepFretSimulate/simulation_test.py
TraceAnalyser/DeepFretSimulate/utils.py
TraceAnalyser/InceptionTime/__init__.py
TraceAnalyser/InceptionTime/models/inceptiontime_model_240724_1116.h5
TraceAnalyser/funcs/__init__.py
TraceAnalyser/funcs/ebfret_utils.py
TraceAnalyser/funcs/gui_HMM_utils.py
TraceAnalyser/funcs/gui_analysis_plot_utils.py
TraceAnalyser/funcs/gui_bleach_utils.py
TraceAnalyser/funcs/gui_correction_utils.py
TraceAnalyser/funcs/gui_detectcrop_utils.py
TraceAnalyser/funcs/gui_ebfret_utils.py
TraceAnalyser/funcs/gui_export_utils.py
TraceAnalyser/funcs/gui_group_utils.py
TraceAnalyser/funcs/gui_import_utils.py
TraceAnalyser/funcs/gui_inceptiontime_utils.py
TraceAnalyser/funcs/gui_layout.py
TraceAnalyser/funcs/gui_management_utils.py
TraceAnalyser/funcs/gui_measure_plot_utils.py
TraceAnalyser/funcs/gui_simulation_utils.py
TraceAnalyser/funcs/gui_smoothing_utils.py
TraceAnalyser/funcs/gui_trace_plot_overlays.py
TraceAnalyser/funcs/gui_trace_plot_utils.py
TraceAnalyser/funcs/gui_windows.py
TraceAnalyser/funcs/gui_worker.py
ebFRET/__init__.py
ebFRET/ebFRET.m
ebFRET/+ebfret/check_matlab_version.m
ebFRET/+ebfret/check_parfor.m
ebFRET/+ebfret/ebFRET.m
ebFRET/+ebfret/escape_tex.m
ebFRET/+ebfret/join.m
ebFRET/+ebfret/nan_to_zero.m
ebFRET/+ebfret/normalize.m
ebFRET/+ebfret/num_to_str.m
ebFRET/+ebfret/struct_to_keyval.m
ebFRET/+ebfret/+analysis/photobleach_index.m
TraceAnalyser-0.0.6.dist-info/LICENSE
TraceAnalyser-0.0.6.dist-info/METADATA
TraceAnalyser-0.0.6.dist-info/WHEEL
TraceAnalyser-0.0.6.dist-info/entry_points.txt
TraceAnalyser-0.0.6.dist-info/top_level.txt
TraceAnalyser-0.0.6.dist-info/RECORD
