Metadata-Version: 2.1
Name: TraceAnalyser
Version: 0.0.6
Summary: Time Series Analysis Software
Author: Piers Turner
Author-email: piers.turner@physics.ox.ac.uk
License: 
Project-URL: Bug Tracker, https://github.com/piedrro/TraceAnalyser/issues
Project-URL: Documentation, https://github.com/piedrro/TraceAnalyser#README.md
Project-URL: Source Code, https://github.com/piedrro/TraceAnalyser
Project-URL: User Support, https://github.com/piedrro/TraceAnalyser/issues
Classifier: Development Status :: 2 - Pre-Alpha
Classifier: Framework :: napari
Classifier: Intended Audience :: Developers
Classifier: License :: OSI Approved :: BSD License
Classifier: Operating System :: OS Independent
Classifier: Programming Language :: Python
Classifier: Programming Language :: Python :: 3
Classifier: Programming Language :: Python :: 3 :: Only
Classifier: Programming Language :: Python :: 3.9
Classifier: Programming Language :: Python :: 3.10
Classifier: Programming Language :: Python :: 3.11
Classifier: Programming Language :: Python :: 3.12
Classifier: Topic :: Scientific/Engineering :: Image Processing
Requires-Python: >=3.9
License-File: LICENSE
Requires-Dist: numpy
Requires-Dist: qtpy
Requires-Dist: scipy
Requires-Dist: scikit-learn
Requires-Dist: pymatreader
Requires-Dist: pyqtgraph
Requires-Dist: pomegranate ==0.14.8
Requires-Dist: pandas
Requires-Dist: matplotlib
Requires-Dist: tqdm
Requires-Dist: hmmlearn
Requires-Dist: originpro
Requires-Dist: tensorflow[and-cuda]
Requires-Dist: mat4py
Requires-Dist: tsaug
Requires-Dist: tensorboard
Requires-Dist: parmap
Requires-Dist: openpyxl
Requires-Dist: retrying
Requires-Dist: glob2
Requires-Dist: pyqt5-tools
Requires-Dist: torch
Requires-Dist: tsai
Requires-Dist: ipykernel
Provides-Extra: testing
Requires-Dist: tox ; extra == 'testing'
Requires-Dist: pytest ; extra == 'testing'
Requires-Dist: pytest-cov ; extra == 'testing'
Requires-Dist: pytest-qt ; extra == 'testing'
Requires-Dist: napari ; extra == 'testing'
Requires-Dist: pyqt5 ; extra == 'testing'
